{"alumnos_totales": 22, "presentados": 2, "no_presentados": 20, "media": 2.33, "max": 2.83, "min": 1.83, "aprobados": 0, "suspensos": 2, "porcentaje_aprobados": 0.0, "question_data": [{"question": "P1", "avg_score": 0.5, "total_answered": 2, "A": 95.5, "B": 4.5, "C": 9.1, "D": 95.5}, {"question": "P2", "avg_score": 0.0, "total_answered": 2, "A": 0.0, "B": 95.5, "C": 100.0, "D": 90.9}, {"question": "P3", "avg_score": 0.0, "total_answered": 2, "A": 95.5, "B": 0.0, "C": 90.9, "D": 100.0}, {"question": "P4", "avg_score": 0.83, "total_answered": 2, "A": 9.1, "B": 100.0, "C": 95.5, "D": 100.0}, {"question": "P5", "avg_score": 0.75, "total_answered": 2, "A": 100.0, "B": 9.1, "C": 4.5, "D": 100.0}, {"question": "P6", "avg_score": 0.5, "total_answered": 2, "A": 9.1, "B": 100.0, "C": 4.5, "D": 95.5}, {"question": "P7", "avg_score": 0.17, "total_answered": 2, "A": 95.5, "B": 90.9, "C": 100.0, "D": 4.5}, {"question": "P8", "avg_score": 0.0, "total_answered": 2, "A": 100.0, "B": 100.0, "C": 0.0, "D": 90.9}, {"question": "P9", "avg_score": 0.67, "total_answered": 2, "A": 100.0, "B": 4.5, "C": 9.1, "D": 4.5}, {"question": "P10", "avg_score": 0.67, "total_answered": 2, "A": 4.5, "B": 4.5, "C": 9.1, "D": 100.0}], "n_opciones": 4}